pylove2d-0.2.1.dist-info/licenses/LICENSE
src/__init__.py
src/app.py
src/audio.py
src/filesystem.py
src/graphics.py
src/input.py
src/mathutils.py
src/timer.py
src/types.py
src/window.py
pylove2d-0.2.1.dist-info/METADATA
pylove2d-0.2.1.dist-info/WHEEL
pylove2d-0.2.1.dist-info/top_level.txt
pylove2d-0.2.1.dist-info/RECORD
