Metadata-Version: 2.4
Name: pylove2d
Version: 0.2.1
Summary: Python game framework inspired by LÖVE2D
Author: nnei
License: MIT License
Classifier: Programming Language :: Python :: 3
Classifier: License :: OSI Approved :: MIT License
Classifier: Operating System :: OS Independent
Requires-Python: >=3.10
License-File: LICENSE
Requires-Dist: pygame-ce>=2.5.3
Requires-Dist: numpy>=1.24
Dynamic: license-file
Dynamic: requires-python
